cardiotensor/__init__.py
cardiotensor/analysis/__init__.py
cardiotensor/analysis/analysis_functions.py
cardiotensor/analysis/gui_analysis_tool.py
cardiotensor/colormaps/__init__.py
cardiotensor/colormaps/helix_angle.py
cardiotensor/launcher/__init__.py
cardiotensor/launcher/slurm_launcher.py
cardiotensor/orientation/__init__.py
cardiotensor/orientation/orientation_computation_functions.py
cardiotensor/orientation/orientation_computation_pipeline.py
cardiotensor/scripts/analysis_histograms.py
cardiotensor/scripts/analysis_streamlines.py
cardiotensor/scripts/compute_orientation.py
cardiotensor/scripts/convert_trk_to_am.py
cardiotensor/scripts/generate_streamlines.py
cardiotensor/scripts/gui_analysis_tool.py
cardiotensor/scripts/slurm_launcher.py
cardiotensor/scripts/visualize_streamlines.py
cardiotensor/scripts/visualize_vector_field.py
cardiotensor/tractography/__init__.py
cardiotensor/tractography/generate_streamlines.py
cardiotensor/utils/DataReader.py
cardiotensor/utils/__init__.py
cardiotensor/utils/am_utils.py
cardiotensor/utils/downsampling.py
cardiotensor/utils/streamlines_io_utils.py
cardiotensor/utils/utils.py
cardiotensor/utils/vector_vtk_export.py
cardiotensor/visualization/fury_plotting_streamlines.py
cardiotensor/visualization/fury_plotting_vectors.py
cardiotensor/visualization/streamlines.py
cardiotensor/visualization/vector_field.py
cardiotensor-1.1.5.dist-info/licenses/LICENSE
cardiotensor-1.1.5.dist-info/METADATA
cardiotensor-1.1.5.dist-info/WHEEL
cardiotensor-1.1.5.dist-info/entry_points.txt
cardiotensor-1.1.5.dist-info/top_level.txt
cardiotensor-1.1.5.dist-info/RECORD
