Metadata-Version: 2.4
Name: cardiotensor
Version: 1.1.5
Summary: Toolkit designed for quantifying and visualising 3D cardiomyocytes orientations in heart images
Author-email: Joseph Brunet <j.brunet@ucl.ac.uk>
License: MIT License
Project-URL: Documentation, https://www.josephbrunet.fr/cardiotensor/
Project-URL: Issues, https://github.com/JosephBrunet/cardiotensor/issues
Project-URL: Repository, https://github.com/JosephBrunet/cardiotensor
Keywords: cardiotensor, cardiomyocytes, heart, orientation, structure tensor, image processing
Classifier: Operating System :: OS Independent
Classifier: Programming Language :: Python :: 3
Classifier: Programming Language :: Python :: 3 :: Only
Classifier: Programming Language :: Python :: 3.10
Classifier: Programming Language :: Python :: 3.11
Classifier: Programming Language :: Python :: 3.12
Classifier: Programming Language :: Python :: 3.13
Classifier: Environment :: Console
Classifier: Intended Audience :: Science/Research
Classifier: Intended Audience :: Developers
Classifier: License :: OSI Approved :: MIT License
Requires-Python: >=3.10
License-File: LICENSE
Requires-Dist: PyQt5
Requires-Dist: SimpleITK
Requires-Dist: alive_progress
Requires-Dist: dask
Requires-Dist: dipy
Requires-Dist: fury
Requires-Dist: glymur
Requires-Dist: imagecodecs
Requires-Dist: matplotlib
Requires-Dist: nibabel
Requires-Dist: numpy>=1.20
Requires-Dist: opencv-python-headless
Requires-Dist: pandas
Requires-Dist: psutil
Requires-Dist: scikit-image
Requires-Dist: structure-tensor>=0.3.0
Requires-Dist: tifffile
Requires-Dist: tqdm
Provides-Extra: cupy
Requires-Dist: cupy>=8; extra == "cupy"
Provides-Extra: dev
Requires-Dist: black; extra == "dev"
Requires-Dist: mkdocs; extra == "dev"
Requires-Dist: mkdocs-gen-files; extra == "dev"
Requires-Dist: mkdocs-literate-nav; extra == "dev"
Requires-Dist: mkdocs-material; extra == "dev"
Requires-Dist: mkdocs-section-index; extra == "dev"
Requires-Dist: mkdocstrings[python]; extra == "dev"
Requires-Dist: pre-commit; extra == "dev"
Requires-Dist: pytest; extra == "dev"
Requires-Dist: pytest-cov; extra == "dev"
Requires-Dist: ruff; extra == "dev"
Provides-Extra: git
Requires-Dist: mkdocs-git-committers-plugin-2<3,>=1.1; extra == "git"
Requires-Dist: mkdocs-git-revision-date-localized-plugin>=1.2.4,~=1.2; extra == "git"
Requires-Dist: mkdocstrings-python; extra == "git"
Dynamic: license-file
